{
  "sections": {
    "main": {
      "type": "link-list",
      "blocks": {
        "8b5942e0-a8ea-47a7-aca8-25b941404fe4": {
          "type": "link",
          "settings": {
            "collection": "shopify:\/\/pages\/discover-the-gospel-our-story",
            "title": "Our Story",
            "active": true
          }
        },
        "7c9a4720-acf9-47fa-8a57-fd67d696ac12": {
          "type": "link",
          "settings": {
            "collection": "shopify:\/\/pages\/discover-the-gospel-our-community",
            "title": "Our Community",
            "active": false
          }
        }
      },
      "block_order": [
        "8b5942e0-a8ea-47a7-aca8-25b941404fe4",
        "7c9a4720-acf9-47fa-8a57-fd67d696ac12"
      ],
      "settings": {
      }
    },
    "1630024779d99869da": {
      "type": "image-with-text-overlay",
      "settings": {
        "center_all": false,
        "section_link": "",
        "section_size": "normal",
        "image": "shopify:\/\/shop_images\/The_Gospel_Our_Story-Our_Story_copy_677f35a1-844c-4cc6-b5cc-90cc57204ebc.jpg",
        "video": "",
        "text_color": "#ffffff",
        "overlay_color": "#000000",
        "overlay_opacity": 30,
        "text_size": 25,
        "subheading": "",
        "title": "Our Story",
        "content": "<p>Inspired by the divine music that shares its name <em>The Gospel <\/em>was founded on the belief in bringing a distinct Australian approach to a traditional American whiskey to the world.<\/p>",
        "button_1_text": "",
        "button_1_link": "",
        "button_2_text": "",
        "button_2_link": ""
      }
    },
    "1633923516b2c5bd24": {
      "type": "custom-html",
      "settings": {
        "subheading": "",
        "title": "",
        "html": ""
      }
    },
    "162922451101adad1f": {
      "type": "text-with-image",
      "settings": {
        "subheading": "",
        "title": "Discover The Gospel",
        "image": "shopify:\/\/shop_images\/The_Gospel_Our_Story-Discover_The_Gospel.jpg",
        "image_position": "left",
        "bg_colour": "rgba(0,0,0,0)",
        "content": "<p>We use proven techniques of the world’s most famous distilleries, coupled with Melbourne’s dynamic climate to create rye whiskey with passion, integrity and belief.<br\/><br\/>Truth and authenticity is woven into everything we say and do, and we are driven by our passion to shine a light on the unknown and uncover the true spirit of rye.<br\/><br\/>Thank you for following us into the light. <\/p>",
        "title2": "",
        "link_text": "",
        "link_url": "",
        "enable_email": false
      }
    },
    "163056458012c76196": {
      "type": "custom-html",
      "settings": {
        "subheading": "",
        "title": "",
        "html": ""
      }
    },
    "162922446868bb256d": {
      "type": "text-with-image",
      "settings": {
        "subheading": "",
        "title": "LOCALLY MADE",
        "image": "shopify:\/\/shop_images\/The_Gospel_Our_Story-Made_Locally.jpg",
        "image_position": "right",
        "bg_colour": "rgba(0,0,0,0)",
        "content": "<p><em>The Gospel<\/em> is distilled and bottled by fanatics in Brunswick, Melbourne, all of whom have a fierce love for deliciously unpretentious rye whiskey. Our small, dedicated team produce everything by hand under the guidance of <em>Master Distiller<\/em>, Ian Thorn. <br\/><br\/>Ian is the boss of all things booze – he is the first and only distiller to hold the esteemed ‘Master Distiller’ accreditation in Australia. <br\/><br\/>Learn more about his story <a href=\"\/blogs\/journal\/our-people-master-distiller-ian-thorn\" target=\"_blank\" title=\"Our People: Master Distiller Ian Thorn\"><span style=\"text-decoration:underline\">here<\/span><\/a>.<\/p>",
        "title2": "",
        "link_text": "",
        "link_url": "",
        "enable_email": false
      }
    },
    "163002516665a1e199": {
      "type": "custom-html",
      "settings": {
        "subheading": "",
        "title": "",
        "html": ""
      }
    },
    "1629224474d4a0d99e": {
      "type": "text-with-image",
      "settings": {
        "subheading": "",
        "title": "DEDICATION TO RYE",
        "image": "shopify:\/\/shop_images\/The_Gospel_Our_Story-Dedicated_to_Rye.jpg",
        "image_position": "left",
        "bg_colour": "rgba(0,0,0,0)",
        "content": "<p>We are Australia’s only dedicated rye whiskey distillery. <br\/><br\/><em>The Gospel<\/em> is crafted and distilled from 100% Australian unmalted rye, which has been cultivated and nurtured by a single farmer in the Murray Mallee region of South Australia. <br\/><br\/>Specifically chosen for its harsh climate, the rye from this area is small and dense – renowned for its distinct, extraordinary flavour and is unmatched by rye from other areas. <br\/><br\/>Rye whiskey may be the hardest of all whiskeys to distil, but our obsession and dedication makes a damn good drink.<br\/><br\/><\/p>",
        "title2": "",
        "link_text": "",
        "link_url": "",
        "enable_email": false
      }
    },
    "16305647752cd9b3e8": {
      "type": "custom-html",
      "settings": {
        "subheading": "",
        "title": "",
        "html": ""
      }
    },
    "162922448038a251fb": {
      "type": "text-with-image",
      "settings": {
        "subheading": "",
        "title": "A NEW TASTE IN WHISKEY",
        "image": "shopify:\/\/shop_images\/The_Gospel_Our_Story-New_Taste.jpg",
        "image_position": "right",
        "bg_colour": "rgba(0,0,0,0)",
        "content": "<p><em>The Gospel<\/em> embodies the characteristics of traditional American rye whiskey with a flavour nuance that is distinctly Australian. <br\/><br\/>Our unmalted rye grain imparts deep, spicy flavours of vanilla, cinnamon and dried fruit, with developing notes of pepper, grass and grain. <br\/><br\/>We may taste different to the whisk(e)y you're used to drinking but you will discover a quality, premium, New Age whiskey that perfectly balances sweet and savour - as good neat as it is in whiskey-forward cocktails.<\/p>",
        "title2": "",
        "link_text": "",
        "link_url": "",
        "enable_email": false
      }
    },
    "16498372220de6d8ab": {
      "type": "custom-html",
      "settings": {
        "subheading": "",
        "title": "",
        "html": ""
      }
    },
    "1649836500be9b70d5": {
      "type": "text-with-image",
      "settings": {
        "subheading": "",
        "title": "THERE’S MERIT IN A DRINK",
        "image": "shopify:\/\/shop_images\/Cocktail_group_1_6faa7673-a93b-4b13-9360-0afc123ac07d.jpg",
        "image_position": "left",
        "bg_colour": "#f2eee6",
        "content": "<p>At <em>The Gospel<\/em>, we are not just fanatical about rye. We are also passionate about standing up for what we believe in and supporting our community. We recognise our responsibility to operate in a responsible manner and to be conscious of our social impact and environmental footprint. As a growing young business, we continue to learn and evolve, finding more sustainable and socially considered ways of doing things.<br\/><br\/>That’s why we use 100% recyclable packaging, divert our spent waste from landfill and donate 2.5% of net profit to our partner charities. Learn more about the incredible folk we’ve partnered with <a href=\"https:\/\/shop.thegospelwhiskey.com\/pages\/discover-the-gospel-our-community\"><span style=\"text-decoration:underline\">here<\/span><\/a>.<br\/><\/p>",
        "title2": "",
        "link_text": "",
        "link_url": "",
        "enable_email": false
      }
    },
    "163002479889ffe581": {
      "type": "image-with-text-block",
      "disabled": true,
      "settings": {
        "image": "shopify:\/\/shop_images\/unnamed-4_copy.jpg",
        "background": "#ffffff",
        "text_color": "#1c1b1b",
        "block_size": "small",
        "title": "Your story",
        "content": "<p>Add your own custom content to give more information about your store, availability details...<\/p>",
        "button_label": "",
        "button_link": "",
        "show_parallax": true
      }
    },
    "1629224529014cc825": {
      "type": "timeline",
      "disabled": true,
      "blocks": {
        "1629224529014cc825-0": {
          "type": "item",
          "settings": {
            "image": "shopify:\/\/shop_images\/main_static_banner.jpg",
            "apply_overlay": true,
            "title": "2000",
            "subheading": "Sub-heading",
            "heading": "Heading",
            "content": "<p>Add your own custom content to give more information about your store, availability details...<\/p>"
          }
        },
        "1629224529014cc825-1": {
          "type": "item",
          "settings": {
            "apply_overlay": true,
            "title": "2001",
            "subheading": "Sub-heading",
            "heading": "Heading",
            "content": "<p>Add your own custom content to give more information about your store, availability details...<\/p>"
          }
        },
        "1629224529014cc825-2": {
          "type": "item",
          "settings": {
            "apply_overlay": true,
            "title": "2002",
            "subheading": "Sub-heading",
            "heading": "Heading",
            "content": "<p>Add your own custom content to give more information about your store, availability details...<\/p>"
          }
        },
        "04023397-2a4f-42bc-8641-da05543f4f5c": {
          "type": "item",
          "settings": {
            "apply_overlay": true,
            "title": "2000",
            "subheading": "Sub-heading",
            "heading": "Heading",
            "content": "<p>Add your own custom content to give more information about your store, availability details...<\/p>"
          }
        }
      },
      "block_order": [
        "1629224529014cc825-0",
        "1629224529014cc825-1",
        "1629224529014cc825-2",
        "04023397-2a4f-42bc-8641-da05543f4f5c"
      ],
      "settings": {
        "text_color": "rgba(0,0,0,0)"
      }
    },
    "163002519537707cde": {
      "type": "image-with-text-overlay",
      "disabled": true,
      "settings": {
        "center_all": true,
        "section_link": "",
        "section_size": "large",
        "video": "",
        "text_color": "#ffffff",
        "overlay_color": "#000000",
        "overlay_opacity": 30,
        "text_size": 40,
        "subheading": "",
        "title": "Our Ethics",
        "content": "<p>, , sessionable smooth whiskey, Great base for classic cocktails, created by whiskey fanatics<\/p>",
        "button_1_text": "100% Australian rye",
        "button_1_link": "",
        "button_2_text": "independent craft distillery",
        "button_2_link": ""
      }
    },
    "163002481216eb2ab4": {
      "type": "slideshow",
      "disabled": true,
      "blocks": {
        "163002481216eb2ab4-0": {
          "type": "image",
          "settings": {
            "image": "shopify:\/\/shop_images\/About_us_placeholder.jpg",
            "desktop_video": "",
            "mobile_video": "",
            "apply_overlay": true,
            "content_position": "bottomLeft",
            "subheading": "",
            "title": "Our Story",
            "title_mobile": "",
            "content": "<p>Add your own custom content to give more information about your store, availability details...<\/p>",
            "button_1_text": "",
            "button_1_link": "",
            "button_2_text": "",
            "button_2_link": ""
          }
        },
        "163002481216eb2ab4-1": {
          "type": "image",
          "settings": {
            "image": "shopify:\/\/shop_images\/unnamed-4_copy.jpg",
            "desktop_video": "",
            "mobile_video": "",
            "apply_overlay": true,
            "content_position": "bottomLeft",
            "subheading": "",
            "title": "Our Community",
            "title_mobile": "",
            "content": "<p>Add your own custom content to give more information about your store, availability details...<\/p>",
            "button_1_text": "",
            "button_1_link": "",
            "button_2_text": "",
            "button_2_link": ""
          }
        }
      },
      "block_order": [
        "163002481216eb2ab4-0",
        "163002481216eb2ab4-1"
      ],
      "settings": {
        "show_fullscreen": false,
        "show_arrow": false,
        "autoplay": true,
        "cycle_speed": 5,
        "text_color": "#ffffff",
        "text_size": 40,
        "button_color": "#363636",
        "button_background": "#ffffff"
      }
    },
    "1630024833ec9bbc7d": {
      "type": "about-us",
      "disabled": true,
      "settings": {
        "subheading": "RYE IS THE GOSPEL",
        "title": "WHISKEY IS RELIGION",
        "html": "<p>It is widely believed that whiskey was first distilled for medicinal use by monks and apothecaries in Scotland and Ireland. The distillation of whiskey evolved as it moved from monastic to secular, as it did with the path of migration over hundreds of years. Early Scotch-Irish settlers in the USA used rye to make whiskey because barley didn’t adapt to the North American climate. These conditions are also true for the dry climate of Australia, where we set out to reimagine this original American spirit using 100% Australian rye.<\/p>"
      }
    }
  },
  "order": [
    "main",
    "1630024779d99869da",
    "1633923516b2c5bd24",
    "162922451101adad1f",
    "163056458012c76196",
    "162922446868bb256d",
    "163002516665a1e199",
    "1629224474d4a0d99e",
    "16305647752cd9b3e8",
    "162922448038a251fb",
    "16498372220de6d8ab",
    "1649836500be9b70d5",
    "163002479889ffe581",
    "1629224529014cc825",
    "163002519537707cde",
    "163002481216eb2ab4",
    "1630024833ec9bbc7d"
  ]
}
